end_of_file/__init__.py
end_of_file-1.1.0.dist-info/LICENSE
end_of_file-1.1.0.dist-info/METADATA
end_of_file-1.1.0.dist-info/WHEEL
end_of_file-1.1.0.dist-info/entry_points.txt
end_of_file-1.1.0.dist-info/top_level.txt
end_of_file-1.1.0.dist-info/RECORD
