Metadata-Version: 2.1
Name: end-of-file
Version: 1.1.0
Summary: Small utility to ensure files end with one newline.
Home-page: https://github.com/Keeo/end-of-file
Author: Martin Moravek
Author-email: moravek.martin@gmail.com
License: UNKNOWN
Project-URL: Bug Tracker, https://github.com/Keeo/end-of-file/issues
Platform: UNKNOWN
Classifier: Intended Audience :: Developers
Classifier: License :: OSI Approved :: BSD License
Classifier: Operating System :: OS Independent
Classifier: Programming Language :: Python
Requires-Python: >=3.6
License-File: LICENSE
Requires-Dist: Click
